SCONe/PhotoUtils.py
SCONe/__init__.py
SCONe/blackbody_tools.py
SNeSCOPE/PhotoUtils.py
SNeSCOPE/__init__.py
SNeSCOPE/blackbody_tools.py
SNeSCOPE-1.0.3.dist-info/LICENSE
SNeSCOPE-1.0.3.dist-info/METADATA
SNeSCOPE-1.0.3.dist-info/WHEEL
SNeSCOPE-1.0.3.dist-info/top_level.txt
SNeSCOPE-1.0.3.dist-info/RECORD
