Metadata-Version: 2.1
Name: SNeSCOPE
Version: 1.0.3
Summary: Published version (April 2024)
Home-page: https://github.com/idoirani/shock_cooling
Author: Ido Irani
Author-email: idoirani@gmail.com
License: UNKNOWN
Keywords: astronomy
Platform: UNKNOWN
Requires-Python: >=3.6
License-File: LICENSE
Requires-Dist: numpy
Requires-Dist: matplotlib
Requires-Dist: dynesty
Requires-Dist: scipy
Requires-Dist: numba
Requires-Dist: astropy
Requires-Dist: pandas
Requires-Dist: tqdm
Requires-Dist: ipdb
Requires-Dist: extinction
